README.md
setup.cfg
setup.py
bin/itgw433-capture
pyitgw433/__init__.py
pyitgw433/cli.py
pyitgw433/pdu.py
pyitgw433.egg-info/PKG-INFO
pyitgw433.egg-info/SOURCES.txt
pyitgw433.egg-info/dependency_links.txt
pyitgw433.egg-info/entry_points.txt
pyitgw433.egg-info/not-zip-safe
pyitgw433.egg-info/requires.txt
pyitgw433.egg-info/top_level.txt